hdl_call_if/__build_num__.py
hdl_call_if/__init__.py
hdl_call_if/__main__.py
hdl_call_if/call_proxy.py
hdl_call_if/decorators.py
hdl_call_if/hdl_call_endpoint.py
hdl_call_if/pkginfo.py
hdl_call_if/vpi.py
pyhdl_call_if-0.0.1.8682446142.dist-info/LICENSE
pyhdl_call_if-0.0.1.8682446142.dist-info/METADATA
pyhdl_call_if-0.0.1.8682446142.dist-info/WHEEL
pyhdl_call_if-0.0.1.8682446142.dist-info/entry_points.txt
pyhdl_call_if-0.0.1.8682446142.dist-info/top_level.txt
pyhdl_call_if-0.0.1.8682446142.dist-info/RECORD
